async_task_queue/__init__.py
async_task_queue/async_task_queue.py
async_task_queue/render.py
async_task_queue-0.1.2.dist-info/LICENSE.md
async_task_queue-0.1.2.dist-info/WHEEL
async_task_queue-0.1.2.dist-info/METADATA
async_task_queue-0.1.2.dist-info/RECORD
