Metadata-Version: 2.1
Name: async-task-queue
Version: 0.1.2
Summary: In-memory FIFO queue for concurrent task execution
Home-page: https://github.com/NarrativeScience/async-task-queue
License: BSD-3-Clause
Keywords: asyncio, async queue
Author: Celestine Kao
Author-email: ckao@narrativescience.com
Requires-Python: >=3.6,<4
Classifier: Intended Audience :: Developers
Classifier: License :: OSI Approved :: BSD License
Classifier: Programming Language :: Python :: 3
Classifier: Topic :: Software Development :: Libraries :: Python Modules
